{
  "examTitle": "ข้อสอบปราบปราม68",
  "examSubtitle": "สอบสวนกลางปราบปราม",
  "totalQuestions": 150,
  "examTimeSeconds": 5400,
  "passPercent": 60,
  "questions": [
    {
      "no": 1,
      "question": "2 + 2 = ?",
      "options": ["3", "4", "5", "6"],
      "answer": "4",
      "subject": "คณิตศาสตร์"
    },
    {
      "no": 2,
      "question": "เมืองหลวงของไทยคืออะไร?",
      "options": ["เชียงใหม่", "กรุงเทพมหานคร", "ขอนแก่น", "ภูเก็ต"],
      "answer": "กรุงเทพมหานคร",
      "subject": "สังคมศึกษา"
    },
    {
      "no": 3,
      "question": "กฎหมายอาญามาตราเกี่ยวกับการลักทรัพย์คือข้อใด?",
      "options": ["มาตรา 334", "มาตรา 288", "มาตรา 112", "มาตรา 326"],
      "answer": "มาตรา 334",
      "subject": "กฎหมาย"
    },
    {
      "no": 4,
      "question": "5 × 5 = ?",
      "options": ["10", "20", "25", "30"],
      "answer": "25",
      "subject": "คณิตศาสตร์"
    },
    {
      "no": 5,
      "question": "ประเทศไทยมีกี่จังหวัด?",
      "options": ["75", "76", "77", "78"],
      "answer": "77",
      "subject": "สังคมศึกษา"
    },
    {
      "no": 6,
      "question": "พ.ร.บ. ตำรวจแห่งชาติ พ.ศ. 2565 มีผลบังคับใช้เมื่อใด?",
      "options": ["16 ต.ค. 2565", "17 ต.ค. 2565", "18 ต.ค. 2565", "19 ต.ค. 2565"],
      "answer": "16 ต.ค. 2565",
      "subject": "กฎหมาย"
    },
    {
      "no": 7,
      "question": "12 × 12 = ?",
      "options": ["124", "132", "144", "156"],
      "answer": "144",
      "subject": "คณิตศาสตร์"
    },
    {
      "no": 8,
      "question": "แม่น้ำที่ยาวที่สุดในประเทศไทยคือแม่น้ำใด?",
      "options": ["แม่น้ำเจ้าพระยา", "แม่น้ำชี", "แม่น้ำมูล", "แม่น้ำปิง"],
      "answer": "แม่น้ำชี",
      "subject": "สังคมศึกษา"
    },
    {
      "no": 9,
      "question": "ความผิดฐานฆ่าผู้อื่น อยู่ในมาตราใดของประมวลกฎหมายอาญา?",
      "options": ["มาตรา 280", "มาตรา 288", "มาตรา 290", "มาตรา 295"],
      "answer": "มาตรา 288",
      "subject": "กฎหมาย"
    },
    {
      "no": 10,
      "question": "√81 = ?",
      "options": ["7", "8", "9", "10"],
      "answer": "9",
      "subject": "คณิตศาสตร์"
    },
    {
      "no": 11,
      "question": "วันจักรี ตรงกับวันที่เท่าใด?",
      "options": ["5 เมษายน", "6 เมษายน", "13 เมษายน", "14 เมษายน"],
      "answer": "6 เมษายน",
      "subject": "สังคมศึกษา"
    },
    {
      "no": 12,
      "question": "การจับกุมโดยไม่มีหมายจับ สามารถทำได้ตาม ป.วิ.อ. มาตราใด?",
      "options": ["มาตรา 66", "มาตรา 78", "มาตรา 80", "มาตรา 92"],
      "answer": "มาตรา 78",
      "subject": "กฎหมาย"
    },
    {
      "no": 13,
      "question": "15% ของ 200 คือเท่าใด?",
      "options": ["20", "25", "30", "35"],
      "answer": "30",
      "subject": "คณิตศาสตร์"
    },
    {
      "no": 14,
      "question": "รัฐธรรมนูญแห่งราชอาณาจักรไทย ฉบับปัจจุบัน ประกาศใช้เมื่อ พ.ศ. ใด?",
      "options": ["พ.ศ. 2557", "พ.ศ. 2558", "พ.ศ. 2559", "พ.ศ. 2560"],
      "answer": "พ.ศ. 2560",
      "subject": "กฎหมาย"
    },
    {
      "no": 15,
      "question": "ภูเขาที่สูงที่สุดในประเทศไทยคือยอดเขาใด?",
      "options": ["ดอยอินทนนท์", "ดอยสุเทพ", "ภูกระดึง", "ภูหลวง"],
      "answer": "ดอยอินทนนท์",
      "subject": "สังคมศึกษา"
    },
    {
      "no": 16,
      "question": "3³ = ?",
      "options": ["9", "18", "27", "36"],
      "answer": "27",
      "subject": "คณิตศาสตร์"
    }
  ]
}
